odoo8_addon_connector_prestashop_catalog_manager-8.0.1.0.3-py2.7-nspkg.pth
odoo8_addon_connector_prestashop_catalog_manager-8.0.1.0.3.dist-info/METADATA
odoo8_addon_connector_prestashop_catalog_manager-8.0.1.0.3.dist-info/RECORD
odoo8_addon_connector_prestashop_catalog_manager-8.0.1.0.3.dist-info/WHEEL
odoo8_addon_connector_prestashop_catalog_manager-8.0.1.0.3.dist-info/namespace_packages.txt
odoo8_addon_connector_prestashop_catalog_manager-8.0.1.0.3.dist-info/top_level.txt
odoo_addons/connector_prestashop_catalog_manager/README.rst
odoo_addons/connector_prestashop_catalog_manager/__init__.py
odoo_addons/connector_prestashop_catalog_manager/__openerp__.py
odoo_addons/connector_prestashop_catalog_manager/connector.py
odoo_addons/connector_prestashop_catalog_manager/product.py
odoo_addons/connector_prestashop_catalog_manager/product_attribute.py
odoo_addons/connector_prestashop_catalog_manager/product_category.py
odoo_addons/connector_prestashop_catalog_manager/product_combination.py
odoo_addons/connector_prestashop_catalog_manager/product_image.py
odoo_addons/connector_prestashop_catalog_manager/i18n/connector_prestashop_catalog_manager.pot
odoo_addons/connector_prestashop_catalog_manager/i18n/es.po
odoo_addons/connector_prestashop_catalog_manager/i18n/fr.po
odoo_addons/connector_prestashop_catalog_manager/static/description/icon.png
odoo_addons/connector_prestashop_catalog_manager/static/description/icon.svg
odoo_addons/connector_prestashop_catalog_manager/views/product_attribute_view.xml
odoo_addons/connector_prestashop_catalog_manager/views/product_image_view.xml
odoo_addons/connector_prestashop_catalog_manager/views/product_view.xml
odoo_addons/connector_prestashop_catalog_manager/wizard/__init__.py
odoo_addons/connector_prestashop_catalog_manager/wizard/active_deactive_products.py
odoo_addons/connector_prestashop_catalog_manager/wizard/active_deactive_products_view.xml
odoo_addons/connector_prestashop_catalog_manager/wizard/export_category.py
odoo_addons/connector_prestashop_catalog_manager/wizard/export_category_view.xml
odoo_addons/connector_prestashop_catalog_manager/wizard/export_multiple_products.py
odoo_addons/connector_prestashop_catalog_manager/wizard/export_multiple_products_view.xml
odoo_addons/connector_prestashop_catalog_manager/wizard/sync_products.py
