Metadata-Version: 2.1
Name: odoo8-addon-connector-prestashop-catalog-manager
Version: 8.0.1.0.3
Summary: Prestashop-Odoo Catalog Manager
Home-page: https://github.com/OCA/connector-prestashop
Author: Akretion,AvanzOSC,Tecnativa,Odoo Community Association (OCA)
Author-email: support@odoo-community.org
License: AGPL-3
Platform: UNKNOWN
Classifier: Programming Language :: Python
Classifier: Framework :: Odoo
Classifier: License :: OSI Approved :: GNU Affero General Public License v3
Requires-Python: ~=2.7
Requires-Dist: odoo8-addon-connector-prestashop
Requires-Dist: odoo (<9.0a,>=8.0a)
